json_include.py
json_include-0.1.4.dist-info/DESCRIPTION.rst
json_include-0.1.4.dist-info/METADATA
json_include-0.1.4.dist-info/RECORD
json_include-0.1.4.dist-info/WHEEL
json_include-0.1.4.dist-info/entry_points.txt
json_include-0.1.4.dist-info/metadata.json
json_include-0.1.4.dist-info/top_level.txt
