Metadata-Version: 2.0
Name: json-include
Version: 0.1.4
Summary: An extension for JSON to support file including
Home-page: https://github.com/reorx/json_include
Author: reorx
Author-email: novoreorx@gmail.com
License: MIT
Platform: UNKNOWN
Classifier: License :: OSI Approved :: MIT License
Classifier: Programming Language :: Python
Classifier: Programming Language :: Python :: 2.7
